geoml_presto-0.0.3.dist-info/licenses/LICENSE
presto/__init__.py
presto/model.py
presto/presto.py
presto/utils.py
presto/dataops/__init__.py
presto/dataops/dataset.py
presto/dataops/main.py
presto/dataops/masking.py
presto/dataops/utils.py
presto/dataops/pipelines/__init__.py
presto/dataops/pipelines/dynamicworld.py
presto/dataops/pipelines/ee_pipeline.py
presto/dataops/pipelines/s1_s2_era5_srtm.py
presto/dataops/pipelines/worldcover2020.py
presto/eval/__init__.py
presto/eval/algae_blooms_eval.py
presto/eval/cropharvest_eval.py
presto/eval/cropharvest_extensions.py
presto/eval/croptype_france_eval.py
presto/eval/eurosat_eval.py
presto/eval/eval.py
presto/eval/fuel_moisture_eval.py
presto/eval/knn.py
presto/eval/treesat_eval.py
geoml_presto-0.0.3.dist-info/METADATA
geoml_presto-0.0.3.dist-info/WHEEL
geoml_presto-0.0.3.dist-info/top_level.txt
geoml_presto-0.0.3.dist-info/RECORD
