Metadata-Version: 2.4
Name: geoml-presto
Version: 0.0.3
Summary: Pretrained Remote Sensing Transformer
Author: PG
Author-email: pgzmnk@gmail.com
Classifier: Programming Language :: Python :: 3
Classifier: License :: Other/Proprietary License
Classifier: Operating System :: OS Independent
Requires-Python: >=3.9
License-File: LICENSE
Requires-Dist: einops>=0.6.0
Requires-Dist: h5py>=3.6.0
Requires-Dist: matplotlib>=3.6.2
Requires-Dist: numpy<2.0.0
Requires-Dist: torch>=2.0
Requires-Dist: tqdm>=4.64.1
Requires-Dist: webdataset>=0.2.31
Requires-Dist: cropharvest>=0.6.0
Requires-Dist: google-cloud-storage>=2.2.1
Requires-Dist: earthengine-api>=0.1.334
Requires-Dist: hurry.filesize>=0.9
Requires-Dist: openmapflow[data]>=0.2.2
Requires-Dist: rioxarray>=0.13.1
Dynamic: author
Dynamic: author-email
Dynamic: classifier
Dynamic: description
Dynamic: description-content-type
Dynamic: license-file
Dynamic: requires-dist
Dynamic: requires-python
Dynamic: summary
